XStatic_svg_edit_moin-2012.11.27.1-py3.13-nspkg.pth
xstatic/pkg/svgedit_moin/__init__.py
xstatic/pkg/svgedit_moin/data/LICENSE
xstatic/pkg/svgedit_moin/data/clipart/moon.svg
xstatic/pkg/svgedit_moin/data/clipart/star.svg
xstatic/pkg/svgedit_moin/data/clipart/sun.svg
xstatic/pkg/svgedit_moin/data/editor/browser-not-supported.html
xstatic/pkg/svgedit_moin/data/editor/browser.js
xstatic/pkg/svgedit_moin/data/editor/contextmenu.js
xstatic/pkg/svgedit_moin/data/editor/draw.js
xstatic/pkg/svgedit_moin/data/editor/embedapi.html
xstatic/pkg/svgedit_moin/data/editor/embedapi.js
xstatic/pkg/svgedit_moin/data/editor/history.js
xstatic/pkg/svgedit_moin/data/editor/jquery.js
xstatic/pkg/svgedit_moin/data/editor/math.js
xstatic/pkg/svgedit_moin/data/editor/path.js
xstatic/pkg/svgedit_moin/data/editor/sanitize.js
xstatic/pkg/svgedit_moin/data/editor/select.js
xstatic/pkg/svgedit_moin/data/editor/svg-editor.css
xstatic/pkg/svgedit_moin/data/editor/svg-editor.html
xstatic/pkg/svgedit_moin/data/editor/svg-editor.js
xstatic/pkg/svgedit_moin/data/editor/svg-editor.manifest
xstatic/pkg/svgedit_moin/data/editor/svgcanvas.js
xstatic/pkg/svgedit_moin/data/editor/svgtransformlist.js
xstatic/pkg/svgedit_moin/data/editor/svgutils.js
xstatic/pkg/svgedit_moin/data/editor/touch.js
xstatic/pkg/svgedit_moin/data/editor/units.js
xstatic/pkg/svgedit_moin/data/editor/canvg/canvg.js
xstatic/pkg/svgedit_moin/data/editor/canvg/rgbcolor.js
xstatic/pkg/svgedit_moin/data/editor/contextmenu/jquery.contextMenu.js
xstatic/pkg/svgedit_moin/data/editor/contextmenu/jquery.contextMenu.min.js
xstatic/pkg/svgedit_moin/data/editor/extensions/closepath_icons.svg
xstatic/pkg/svgedit_moin/data/editor/extensions/ext-arrows.js
xstatic/pkg/svgedit_moin/data/editor/extensions/ext-closepath.js
xstatic/pkg/svgedit_moin/data/editor/extensions/ext-connector.js
xstatic/pkg/svgedit_moin/data/editor/extensions/ext-eyedropper.js
xstatic/pkg/svgedit_moin/data/editor/extensions/ext-foreignobject.js
xstatic_svg_edit_moin-2012.11.27.1.dist-info/METADATA
xstatic_svg_edit_moin-2012.11.27.1.dist-info/WHEEL
xstatic_svg_edit_moin-2012.11.27.1.dist-info/namespace_packages.txt
xstatic_svg_edit_moin-2012.11.27.1.dist-info/top_level.txt
xstatic_svg_edit_moin-2012.11.27.1.dist-info/RECORD
