Metadata-Version: 2.4
Name: XStatic-svg-edit-moin
Version: 2012.11.27.1
Summary: svg-edit-moin 2012.11.27 (XStatic packaging standard)
Home-page: http://code.google.com/p/svg-edit/
Maintainer: Reimar Bauer
Maintainer-email: rb.proj@googlemail.com
License: (same as svg-edit-moin)
Keywords: svgedit_moin xstatic
Platform: any
Dynamic: description
Dynamic: home-page
Dynamic: keywords
Dynamic: license
Dynamic: maintainer
Dynamic: maintainer-email
Dynamic: platform
Dynamic: summary
